ckanext_short_urls-0.0.1-py3.10-nspkg.pth
ckanext/short_urls/__init__.py
ckanext/short_urls/command.py
ckanext/short_urls/logic.py
ckanext/short_urls/model.py
ckanext/short_urls/plugin.py
ckanext/short_urls/assets/styles.css
ckanext/short_urls/assets/webassets.yml
ckanext/short_urls/blueprints/__init__.py
ckanext/short_urls/blueprints/short_urls_blueprint.py
ckanext/short_urls/templates/base.html
ckanext/short_urls/templates/package/resource_read.html
ckanext/short_urls/templates/package/snippets/info.html
ckanext/short_urls/tests/__init__.py
ckanext/short_urls/tests/test_command.py
ckanext/short_urls/tests/test_plugin.py
ckanext_short_urls-0.0.1.dist-info/LICENSE
ckanext_short_urls-0.0.1.dist-info/METADATA
ckanext_short_urls-0.0.1.dist-info/WHEEL
ckanext_short_urls-0.0.1.dist-info/entry_points.txt
ckanext_short_urls-0.0.1.dist-info/namespace_packages.txt
ckanext_short_urls-0.0.1.dist-info/top_level.txt
ckanext_short_urls-0.0.1.dist-info/RECORD
