Metadata-Version: 2.1
Name: ckanext-short-urls
Version: 0.0.1
Summary: Create short URLs for datasets and resources
Home-page: https://github.com/fjelltopp/ckanext-short-urls
Author: Manoj Nathwani
Author-email: manoj@fjelltopp.org
License: AGPL
Keywords: CKAN
Platform: UNKNOWN
Classifier: Development Status :: 4 - Beta
Classifier: License :: OSI Approved :: GNU Affero General Public License v3 or later (AGPLv3+)
Classifier: Programming Language :: Python :: 2.7
License-File: LICENSE
